{
  "name": "Kino",
  "identifier": "com.nicolas.kino.source",
  "subtitle": "Privater Media-Player",
  "apps": [
    {
      "name": "Kino",
      "bundleIdentifier": "com.nicolas.Kino",
      "developerName": "Kinetik",
      "version": "2.9",
      "versionDate": "2026-07-11",
      "downloadURL": "https://github.com/nicolasjankovich-netizen/kino/raw/main/install/Kino.ipa",
      "localizedDescription": "Kino 2.9: TorBox-/Nicht-in-Bibliothek-Filmansicht neu und funktional — Handlung, Besetzung und Bewertungen laden jetzt zuverlaessig (mit Wiederholung bei Serverlast), klar beschrifteter Button \"Zur Bibliothek hinzufuegen\", Info direkt unter den Aktionen. Plus alles aus 2.8 (720p/1080p/4K-Aufloesungen, reparierter Bibliotheks-Screen).",
      "iconURL": "https://raw.githubusercontent.com/nicolasjankovich-netizen/kino/main/kino/Assets.xcassets/AppIcon.appiconset/marketing-1024.png",
      "size": 1298213
    }
  ]
}